myt_sdk-1.1.13.dist-info/licenses/LICENSE
py_myt/__init__.py
py_myt/api_client.py
py_myt/cli.py
py_myt/core.py
py_myt/exceptions.py
py_myt/sdk_manager.py
py_myt/utils.py
myt_sdk-1.1.13.dist-info/METADATA
myt_sdk-1.1.13.dist-info/WHEEL
myt_sdk-1.1.13.dist-info/entry_points.txt
myt_sdk-1.1.13.dist-info/top_level.txt
myt_sdk-1.1.13.dist-info/RECORD
