Metadata-Version: 2.4
Name: myt-sdk
Version: 1.1.13
Summary: MYT SDK - 魔云腾SDK通用包，用于自动下载、管理和启动MYT SDK，支持完整的API客户端功能
Home-page: https://github.com/kuqitt/myt_sdk
Download-URL: https://github.com/kuqitt/myt_sdk/archive/v1.0.0.tar.gz
Author: MYT Team
Author-email: kuqitt1@163.com
Maintainer: MYT Team
Maintainer-email: kuqitt1@163.com
Project-URL: Bug Reports, https://github.com/kuqitt/myt_sdk/issues
Project-URL: Source, https://github.com/kuqitt/myt_sdk
Project-URL: Documentation, https://github.com/kuqitt/myt_sdk/blob/main/README.md
Project-URL: Changelog, https://github.com/kuqitt/myt_sdk/blob/main/CHANGELOG.md
Project-URL: API Documentation, https://github.com/kuqitt/myt_sdk/tree/main/docs
Project-URL: Examples, https://github.com/kuqitt/myt_sdk/tree/main/examples
Keywords: myt,sdk,automation,android,container,api,client,device,management,camera,sensor,location,proxy,video,streaming,rtmp,webrtc,monitoring,github
Platform: Windows
Classifier: Development Status :: 5 - Production/Stable
Classifier: Intended Audience :: Developers
Classifier: Intended Audience :: System Administrators
Classifier: License :: OSI Approved :: MIT License
Classifier: Operating System :: Microsoft :: Windows
Classifier: Operating System :: POSIX :: Linux
Classifier: Operating System :: MacOS :: MacOS X
Classifier: Programming Language :: Python :: 3
Classifier: Programming Language :: Python :: 3.7
Classifier: Programming Language :: Python :: 3.8
Classifier: Programming Language :: Python :: 3.9
Classifier: Programming Language :: Python :: 3.10
Classifier: Programming Language :: Python :: 3.11
Classifier: Programming Language :: Python :: 3.12
Classifier: Programming Language :: Python :: 3 :: Only
Classifier: Topic :: Software Development :: Libraries :: Python Modules
Classifier: Topic :: System :: Systems Administration
Classifier: Topic :: Internet :: WWW/HTTP :: Dynamic Content
Classifier: Topic :: Multimedia :: Video
Classifier: Topic :: Scientific/Engineering :: Interface Engine/Protocol Translator
Classifier: Environment :: Console
Classifier: Natural Language :: Chinese (Simplified)
Classifier: Natural Language :: English
Requires-Python: >=3.7
License-File: LICENSE
Requires-Dist: requests>=2.25.0
Requires-Dist: psutil>=5.8.0
Provides-Extra: dev
Requires-Dist: pytest>=6.0; extra == "dev"
Requires-Dist: pytest-cov>=2.0; extra == "dev"
Requires-Dist: black>=21.0; extra == "dev"
Requires-Dist: flake8>=3.8; extra == "dev"
Requires-Dist: mypy>=0.800; extra == "dev"
Requires-Dist: twine>=3.0; extra == "dev"
Requires-Dist: wheel>=0.36; extra == "dev"
Requires-Dist: setuptools>=45.0; extra == "dev"
Provides-Extra: monitoring
Requires-Dist: matplotlib>=3.0; extra == "monitoring"
Requires-Dist: pandas>=1.0; extra == "monitoring"
Provides-Extra: docs
Requires-Dist: sphinx>=3.0; extra == "docs"
Requires-Dist: sphinx-rtd-theme>=0.5; extra == "docs"
Provides-Extra: all
Requires-Dist: pytest>=6.0; extra == "all"
Requires-Dist: pytest-cov>=2.0; extra == "all"
Requires-Dist: black>=21.0; extra == "all"
Requires-Dist: flake8>=3.8; extra == "all"
Requires-Dist: mypy>=0.800; extra == "all"
Requires-Dist: twine>=3.0; extra == "all"
Requires-Dist: wheel>=0.36; extra == "all"
Requires-Dist: setuptools>=45.0; extra == "all"
Requires-Dist: matplotlib>=3.0; extra == "all"
Requires-Dist: pandas>=1.0; extra == "all"
Requires-Dist: sphinx>=3.0; extra == "all"
Requires-Dist: sphinx-rtd-theme>=0.5; extra == "all"
Dynamic: author
Dynamic: author-email
Dynamic: classifier
Dynamic: description
Dynamic: description-content-type
Dynamic: download-url
Dynamic: home-page
Dynamic: keywords
Dynamic: license-file
Dynamic: maintainer
Dynamic: maintainer-email
Dynamic: platform
Dynamic: project-url
Dynamic: provides-extra
Dynamic: requires-dist
Dynamic: requires-python
Dynamic: summary
